src/__init__.py
src/get_anthroscore.py
anthroscore_eacl-0.0.2.dist-info/LICENSE
anthroscore_eacl-0.0.2.dist-info/METADATA
anthroscore_eacl-0.0.2.dist-info/WHEEL
anthroscore_eacl-0.0.2.dist-info/top_level.txt
anthroscore_eacl-0.0.2.dist-info/RECORD
